main.py
harpcli-0.1.2.dist-info/METADATA
harpcli-0.1.2.dist-info/WHEEL
harpcli-0.1.2.dist-info/entry_points.txt
harpcli-0.1.2.dist-info/top_level.txt
harpcli-0.1.2.dist-info/RECORD
