Metadata-Version: 2.1
Name: harpcli
Version: 0.1.2
Summary: CLI for the harp API
Author: harpdevs
License: MIT
Requires-Dist: typer
Requires-Dist: requests
